[{"x": 610, "y": 1102, "width": 188, "height": 240}, {"x": 608, "y": 1102, "width": 196, "height": 248}, {"x": 610, "y": 1102, "width": 192, "height": 244}, {"x": 614, "y": 1108, "width": 188, "height": 240}, {"x": 616, "y": 1112, "width": 180, "height": 230}, {"x": 614, "y": 1108, "width": 188, "height": 240}, {"x": 612, "y": 1108, "width": 192, "height": 244}, {"x": 610, "y": 1104, "width": 196, "height": 248}, {"x": 606, "y": 1096, "width": 204, "height": 258}, {"x": 608, "y": 1094, "width": 204, "height": 258}, {"x": 604, "y": 1084, "width": 216, "height": 274}, {"x": 604, "y": 1082, "width": 220, "height": 280}, {"x": 606, "y": 1082, "width": 220, "height": 280}, {"x": 604, "y": 1078, "width": 224, "height": 286}, {"x": 604, "y": 1074, "width": 230, "height": 292}, {"x": 602, "y": 1072, "width": 234, "height": 298}, {"x": 600, "y": 1066, "width": 238, "height": 304}, {"x": 600, "y": 1064, "width": 244, "height": 310}, {"x": 596, "y": 1064, "width": 244, "height": 310}, {"x": 600, "y": 1068, "width": 238, "height": 304}, {"x": 606, "y": 1072, "width": 234, "height": 298}, {"x": 604, "y": 1072, "width": 230, "height": 292}, {"x": 600, "y": 1068, "width": 234, "height": 298}, {"x": 602, "y": 1068, "width": 234, "height": 298}, {"x": 600, "y": 1066, "width": 238, "height": 304}, {"x": 600, "y": 1064, "width": 244, "height": 310}, {"x": 600, "y": 1066, "width": 238, "height": 304}, {"x": 602, "y": 1070, "width": 234, "height": 298}, {"x": 602, "y": 1070, "width": 234, "height": 298}, {"x": 604, "y": 1074, "width": 230, "height": 292}, {"x": 604, "y": 1074, "width": 230, "height": 292}, {"x": 600, "y": 1072, "width": 234, "height": 298}, {"x": 598, "y": 1074, "width": 234, "height": 298}, {"x": 596, "y": 1074, "width": 234, "height": 298}, {"x": 600, "y": 1078, "width": 230, "height": 292}, {"x": 600, "y": 1082, "width": 224, "height": 286}, {"x": 602, "y": 1082, "width": 224, "height": 286}, {"x": 602, "y": 1084, "width": 224, "height": 286}, {"x": 600, "y": 1082, "width": 224, "height": 286}, {"x": 600, "y": 1084, "width": 224, "height": 286}, {"x": 600, "y": 1082, "width": 224, "height": 286}, {"x": 600, "y": 1084, "width": 224, "height": 286}, {"x": 598, "y": 1084, "width": 224, "height": 286}, {"x": 600, "y": 1086, "width": 220, "height": 280}, {"x": 596, "y": 1082, "width": 224, "height": 286}, {"x": 596, "y": 1084, "width": 224, "height": 286}, {"x": 596, "y": 1084, "width": 224, "height": 286}, {"x": 594, "y": 1084, "width": 224, "height": 286}, {"x": 594, "y": 1084, "width": 224, "height": 286}, {"x": 596, "y": 1084, "width": 224, "height": 286}, {"x": 596, "y": 1086, "width": 224, "height": 286}, {"x": 594, "y": 1084, "width": 224, "height": 286}, {"x": 596, "y": 1086, "width": 224, "height": 286}, {"x": 598, "y": 1084, "width": 224, "height": 286}, {"x": 598, "y": 1086, "width": 224, "height": 286}, {"x": 600, "y": 1090, "width": 220, "height": 280}, {"x": 604, "y": 1096, "width": 212, "height": 270}, {"x": 604, "y": 1094, "width": 216, "height": 274}, {"x": 602, "y": 1090, "width": 220, "height": 280}, {"x": 602, "y": 1092, "width": 216, "height": 274}, {"x": 602, "y": 1092, "width": 216, "height": 274}, {"x": 600, "y": 1092, "width": 216, "height": 274}, {"x": 602, "y": 1094, "width": 216, "height": 274}, {"x": 602, "y": 1092, "width": 216, "height": 274}, {"x": 600, "y": 1092, "width": 216, "height": 274}, {"x": 600, "y": 1092, "width": 216, "height": 274}, {"x": 598, "y": 1092, "width": 216, "height": 274}, {"x": 602, "y": 1096, "width": 212, "height": 270}, {"x": 602, "y": 1096, "width": 212, "height": 270}, {"x": 602, "y": 1096, "width": 212, "height": 270}, {"x": 602, "y": 1096, "width": 212, "height": 270}, {"x": 602, "y": 1096, "width": 216, "height": 274}, {"x": 600, "y": 1094, "width": 216, "height": 274}, {"x": 600, "y": 1096, "width": 216, "height": 274}, {"x": 600, "y": 1096, "width": 216, "height": 274}, {"x": 602, "y": 1098, "width": 212, "height": 270}, {"x": 602, "y": 1100, "width": 212, "height": 270}, {"x": 602, "y": 1100, "width": 212, "height": 270}, {"x": 602, "y": 1102, "width": 212, "height": 270}, {"x": 600, "y": 1102, "width": 212, "height": 270}, {"x": 602, "y": 1104, "width": 208, "height": 264}, {"x": 602, "y": 1102, "width": 208, "height": 264}, {"x": 600, "y": 1098, "width": 212, "height": 270}, {"x": 598, "y": 1094, "width": 212, "height": 270}, {"x": 602, "y": 1096, "width": 208, "height": 264}, {"x": 602, "y": 1094, "width": 208, "height": 264}, {"x": 600, "y": 1094, "width": 208, "height": 264}, {"x": 602, "y": 1094, "width": 208, "height": 264}, {"x": 602, "y": 1094, "width": 208, "height": 264}, {"x": 602, "y": 1094, "width": 208, "height": 264}, {"x": 602, "y": 1094, "width": 212, "height": 270}, {"x": 602, "y": 1094, "width": 212, "height": 270}, {"x": 600, "y": 1092, "width": 216, "height": 274}, {"x": 598, "y": 1092, "width": 216, "height": 274}, {"x": 596, "y": 1092, "width": 216, "height": 274}, {"x": 598, "y": 1094, "width": 216, "height": 274}, {"x": 598, "y": 1094, "width": 216, "height": 274}, {"x": 596, "y": 1094, "width": 216, "height": 274}, {"x": 596, "y": 1094, "width": 216, "height": 274}, {"x": 596, "y": 1096, "width": 216, "height": 274}, {"x": 592, "y": 1092, "width": 220, "height": 280}, {"x": 592, "y": 1092, "width": 220, "height": 280}, {"x": 592, "y": 1092, "width": 220, "height": 280}, {"x": 590, "y": 1090, "width": 220, "height": 280}, {"x": 592, "y": 1092, "width": 220, "height": 280}, {"x": 590, "y": 1090, "width": 224, "height": 286}, {"x": 590, "y": 1088, "width": 224, "height": 286}, {"x": 590, "y": 1090, "width": 224, "height": 286}, {"x": 590, "y": 1088, "width": 224, "height": 286}, {"x": 592, "y": 1090, "width": 220, "height": 280}, {"x": 592, "y": 1090, "width": 220, "height": 280}, {"x": 592, "y": 1090, "width": 220, "height": 280}, {"x": 590, "y": 1088, "width": 220, "height": 280}, {"x": 592, "y": 1088, "width": 220, "height": 280}, {"x": 592, "y": 1088, "width": 220, "height": 280}, {"x": 592, "y": 1086, "width": 220, "height": 280}, {"x": 592, "y": 1086, "width": 220, "height": 280}, {"x": 592, "y": 1086, "width": 220, "height": 280}, {"x": 592, "y": 1084, "width": 220, "height": 280}, {"x": 592, "y": 1086, "width": 220, "height": 280}, {"x": 592, "y": 1086, "width": 220, "height": 280}, {"x": 592, "y": 1086, "width": 220, "height": 280}, {"x": 592, "y": 1086, "width": 220, "height": 280}, {"x": 592, "y": 1086, "width": 220, "height": 280}, {"x": 592, "y": 1084, "width": 220, "height": 280}, {"x": 592, "y": 1084, "width": 220, "height": 280}, {"x": 594, "y": 1084, "width": 220, "height": 280}, {"x": 594, "y": 1084, "width": 220, "height": 280}, {"x": 592, "y": 1082, "width": 224, "height": 286}, {"x": 594, "y": 1084, "width": 220, "height": 280}, {"x": 592, "y": 1082, "width": 224, "height": 286}, {"x": 590, "y": 1082, "width": 224, "height": 286}, {"x": 592, "y": 1082, "width": 224, "height": 286}, {"x": 592, "y": 1082, "width": 224, "height": 286}, {"x": 592, "y": 1082, "width": 224, "height": 286}, {"x": 592, "y": 1082, "width": 224, "height": 286}, {"x": 590, "y": 1082, "width": 224, "height": 286}, {"x": 592, "y": 1082, "width": 224, "height": 286}, {"x": 590, "y": 1084, "width": 224, "height": 286}, {"x": 590, "y": 1084, "width": 224, "height": 286}, {"x": 590, "y": 1084, "width": 224, "height": 286}, {"x": 590, "y": 1084, "width": 224, "height": 286}, {"x": 590, "y": 1084, "width": 224, "height": 286}, {"x": 590, "y": 1086, "width": 224, "height": 286}, {"x": 590, "y": 1086, "width": 224, "height": 286}, {"x": 588, "y": 1084, "width": 224, "height": 286}, {"x": 590, "y": 1086, "width": 224, "height": 286}, {"x": 588, "y": 1086, "width": 224, "height": 286}, {"x": 590, "y": 1088, "width": 224, "height": 286}, {"x": 588, "y": 1088, "width": 224, "height": 286}, {"x": 590, "y": 1088, "width": 224, "height": 286}, {"x": 590, "y": 1088, "width": 224, "height": 286}, {"x": 590, "y": 1088, "width": 224, "height": 286}, {"x": 590, "y": 1088, "width": 224, "height": 286}, {"x": 588, "y": 1088, "width": 224, "height": 286}, {"x": 588, "y": 1090, "width": 224, "height": 286}, {"x": 588, "y": 1088, "width": 224, "height": 286}, {"x": 588, "y": 1088, "width": 224, "height": 286}, {"x": 590, "y": 1088, "width": 224, "height": 286}, {"x": 590, "y": 1088, "width": 224, "height": 286}, {"x": 588, "y": 1086, "width": 224, "height": 286}, {"x": 590, "y": 1088, "width": 224, "height": 286}, {"x": 590, "y": 1088, "width": 224, "height": 286}, {"x": 588, "y": 1086, "width": 224, "height": 286}, {"x": 590, "y": 1088, "width": 224, "height": 286}, {"x": 588, "y": 1088, "width": 224, "height": 286}, {"x": 592, "y": 1090, "width": 220, "height": 280}, {"x": 590, "y": 1088, "width": 224, "height": 286}, {"x": 590, "y": 1090, "width": 220, "height": 280}, {"x": 588, "y": 1088, "width": 224, "height": 286}, {"x": 588, "y": 1088, "width": 224, "height": 286}, {"x": 588, "y": 1088, "width": 224, "height": 286}, {"x": 588, "y": 1088, "width": 224, "height": 286}, {"x": 588, "y": 1088, "width": 224, "height": 286}, {"x": 588, "y": 1088, "width": 224, "height": 286}, {"x": 588, "y": 1086, "width": 224, "height": 286}, {"x": 588, "y": 1088, "width": 224, "height": 286}, {"x": 588, "y": 1088, "width": 224, "height": 286}, {"x": 588, "y": 1086, "width": 224, "height": 286}, {"x": 588, "y": 1086, "width": 224, "height": 286}, {"x": 588, "y": 1084, "width": 224, "height": 286}, {"x": 588, "y": 1084, "width": 224, "height": 286}, {"x": 588, "y": 1084, "width": 224, "height": 286}, {"x": 588, "y": 1084, "width": 224, "height": 286}, {"x": 588, "y": 1082, "width": 224, "height": 286}, {"x": 588, "y": 1084, "width": 224, "height": 286}, {"x": 588, "y": 1082, "width": 224, "height": 286}, {"x": 588, "y": 1082, "width": 224, "height": 286}, {"x": 590, "y": 1082, "width": 224, "height": 286}, {"x": 590, "y": 1082, "width": 224, "height": 286}, {"x": 590, "y": 1082, "width": 224, "height": 286}, {"x": 590, "y": 1082, "width": 224, "height": 286}, {"x": 588, "y": 1080, "width": 224, "height": 286}, {"x": 590, "y": 1080, "width": 224, "height": 286}, {"x": 590, "y": 1080, "width": 224, "height": 286}, {"x": 590, "y": 1082, "width": 224, "height": 286}, {"x": 586, "y": 1078, "width": 230, "height": 292}, {"x": 592, "y": 1082, "width": 224, "height": 286}, {"x": 590, "y": 1080, "width": 224, "height": 286}, {"x": 590, "y": 1082, "width": 224, "height": 286}, {"x": 590, "y": 1082, "width": 224, "height": 286}, {"x": 586, "y": 1078, "width": 230, "height": 292}, {"x": 588, "y": 1078, "width": 230, "height": 292}, {"x": 588, "y": 1080, "width": 230, "height": 292}, {"x": 588, "y": 1078, "width": 230, "height": 292}, {"x": 588, "y": 1080, "width": 230, "height": 292}, {"x": 588, "y": 1080, "width": 230, "height": 292}, {"x": 588, "y": 1080, "width": 230, "height": 292}, {"x": 588, "y": 1080, "width": 230, "height": 292}, {"x": 588, "y": 1080, "width": 230, "height": 292}, {"x": 586, "y": 1080, "width": 230, "height": 292}, {"x": 588, "y": 1080, "width": 230, "height": 292}, {"x": 586, "y": 1080, "width": 230, "height": 292}, {"x": 588, "y": 1080, "width": 230, "height": 292}, {"x": 586, "y": 1080, "width": 230, "height": 292}, {"x": 590, "y": 1084, "width": 224, "height": 286}, {"x": 588, "y": 1082, "width": 224, "height": 286}, {"x": 590, "y": 1084, "width": 224, "height": 286}, {"x": 590, "y": 1084, "width": 224, "height": 286}, {"x": 588, "y": 1080, "width": 230, "height": 292}, {"x": 588, "y": 1080, "width": 230, "height": 292}, {"x": 588, "y": 1082, "width": 230, "height": 292}, {"x": 588, "y": 1082, "width": 230, "height": 292}, {"x": 588, "y": 1080, "width": 230, "height": 292}, {"x": 586, "y": 1080, "width": 230, "height": 292}, {"x": 590, "y": 1084, "width": 224, "height": 286}, {"x": 588, "y": 1080, "width": 230, "height": 292}, {"x": 588, "y": 1080, "width": 230, "height": 292}, {"x": 588, "y": 1080, "width": 230, "height": 292}, {"x": 586, "y": 1080, "width": 230, "height": 292}, {"x": 586, "y": 1080, "width": 230, "height": 292}, {"x": 588, "y": 1080, "width": 230, "height": 292}, {"x": 586, "y": 1080, "width": 230, "height": 292}, {"x": 588, "y": 1082, "width": 230, "height": 292}, {"x": 586, "y": 1080, "width": 230, "height": 292}, {"x": 586, "y": 1080, "width": 230, "height": 292}, {"x": 588, "y": 1080, "width": 230, "height": 292}, {"x": 586, "y": 1078, "width": 230, "height": 292}, {"x": 588, "y": 1080, "width": 230, "height": 292}, {"x": 586, "y": 1078, "width": 230, "height": 292}, {"x": 586, "y": 1078, "width": 230, "height": 292}, {"x": 588, "y": 1078, "width": 230, "height": 292}, {"x": 586, "y": 1076, "width": 230, "height": 292}, {"x": 586, "y": 1078, "width": 230, "height": 292}, {"x": 588, "y": 1078, "width": 230, "height": 292}, {"x": 588, "y": 1076, "width": 230, "height": 292}, {"x": 586, "y": 1076, "width": 230, "height": 292}, {"x": 588, "y": 1078, "width": 230, "height": 292}, {"x": 586, "y": 1076, "width": 230, "height": 292}, {"x": 586, "y": 1076, "width": 230, "height": 292}, {"x": 590, "y": 1078, "width": 224, "height": 286}, {"x": 588, "y": 1078, "width": 224, "height": 286}, {"x": 588, "y": 1078, "width": 224, "height": 286}, {"x": 588, "y": 1076, "width": 224, "height": 286}, {"x": 588, "y": 1078, "width": 224, "height": 286}, {"x": 588, "y": 1076, "width": 224, "height": 286}, {"x": 588, "y": 1076, "width": 224, "height": 286}, {"x": 588, "y": 1076, "width": 224, "height": 286}, {"x": 588, "y": 1076, "width": 224, "height": 286}, {"x": 588, "y": 1076, "width": 224, "height": 286}, {"x": 588, "y": 1076, "width": 224, "height": 286}, {"x": 588, "y": 1076, "width": 224, "height": 286}, {"x": 588, "y": 1076, "width": 224, "height": 286}, {"x": 588, "y": 1076, "width": 224, "height": 286}, {"x": 588, "y": 1078, "width": 224, "height": 286}, {"x": 586, "y": 1074, "width": 230, "height": 292}, {"x": 588, "y": 1078, "width": 224, "height": 286}, {"x": 588, "y": 1076, "width": 224, "height": 286}, {"x": 586, "y": 1076, "width": 224, "height": 286}, {"x": 590, "y": 1080, "width": 220, "height": 280}, {"x": 584, "y": 1072, "width": 230, "height": 292}, {"x": 584, "y": 1070, "width": 234, "height": 298}, {"x": 580, "y": 1068, "width": 238, "height": 304}, {"x": 582, "y": 1068, "width": 238, "height": 304}, {"x": 582, "y": 1066, "width": 238, "height": 304}, {"x": 584, "y": 1066, "width": 234, "height": 298}, {"x": 586, "y": 1060, "width": 234, "height": 298}, {"x": 588, "y": 1064, "width": 230, "height": 292}, {"x": 590, "y": 1066, "width": 230, "height": 292}, {"x": 592, "y": 1068, "width": 230, "height": 292}, {"x": 590, "y": 1068, "width": 230, "height": 292}, {"x": 588, "y": 1066, "width": 234, "height": 298}, {"x": 588, "y": 1066, "width": 234, "height": 298}, {"x": 586, "y": 1066, "width": 234, "height": 298}, {"x": 584, "y": 1066, "width": 234, "height": 298}, {"x": 588, "y": 1070, "width": 230, "height": 292}, {"x": 586, "y": 1070, "width": 230, "height": 292}, {"x": 586, "y": 1070, "width": 230, "height": 292}, {"x": 586, "y": 1072, "width": 230, "height": 292}, {"x": 586, "y": 1072, "width": 230, "height": 292}, {"x": 586, "y": 1074, "width": 230, "height": 292}, {"x": 584, "y": 1076, "width": 230, "height": 292}, {"x": 584, "y": 1076, "width": 230, "height": 292}, {"x": 588, "y": 1080, "width": 224, "height": 286}, {"x": 588, "y": 1082, "width": 224, "height": 286}, {"x": 586, "y": 1080, "width": 224, "height": 286}, {"x": 586, "y": 1082, "width": 224, "height": 286}, {"x": 586, "y": 1084, "width": 220, "height": 280}, {"x": 586, "y": 1082, "width": 220, "height": 280}, {"x": 586, "y": 1084, "width": 220, "height": 280}, {"x": 584, "y": 1082, "width": 220, "height": 280}, {"x": 584, "y": 1082, "width": 220, "height": 280}, {"x": 584, "y": 1082, "width": 220, "height": 280}, {"x": 582, "y": 1082, "width": 220, "height": 280}, {"x": 582, "y": 1082, "width": 220, "height": 280}, {"x": 582, "y": 1080, "width": 220, "height": 280}, {"x": 582, "y": 1080, "width": 220, "height": 280}, {"x": 582, "y": 1080, "width": 220, "height": 280}, {"x": 584, "y": 1082, "width": 216, "height": 274}, {"x": 584, "y": 1082, "width": 216, "height": 274}, {"x": 584, "y": 1082, "width": 216, "height": 274}, {"x": 582, "y": 1082, "width": 216, "height": 274}, {"x": 584, "y": 1084, "width": 216, "height": 274}, {"x": 582, "y": 1080, "width": 220, "height": 280}, {"x": 584, "y": 1082, "width": 220, "height": 280}, {"x": 584, "y": 1080, "width": 220, "height": 280}, {"x": 584, "y": 1080, "width": 220, "height": 280}, {"x": 586, "y": 1080, "width": 220, "height": 280}, {"x": 584, "y": 1076, "width": 224, "height": 286}, {"x": 586, "y": 1078, "width": 224, "height": 286}, {"x": 586, "y": 1078, "width": 224, "height": 286}, {"x": 586, "y": 1076, "width": 224, "height": 286}, {"x": 584, "y": 1078, "width": 224, "height": 286}, {"x": 584, "y": 1078, "width": 224, "height": 286}, {"x": 586, "y": 1078, "width": 224, "height": 286}, {"x": 586, "y": 1078, "width": 224, "height": 286}, {"x": 584, "y": 1076, "width": 224, "height": 286}, {"x": 586, "y": 1078, "width": 224, "height": 286}, {"x": 586, "y": 1078, "width": 224, "height": 286}, {"x": 586, "y": 1078, "width": 224, "height": 286}, {"x": 586, "y": 1078, "width": 224, "height": 286}, {"x": 586, "y": 1078, "width": 224, "height": 286}, {"x": 586, "y": 1078, "width": 224, "height": 286}, {"x": 588, "y": 1080, "width": 224, "height": 286}, {"x": 586, "y": 1078, "width": 224, "height": 286}, {"x": 586, "y": 1078, "width": 224, "height": 286}, {"x": 588, "y": 1078, "width": 224, "height": 286}, {"x": 588, "y": 1078, "width": 224, "height": 286}, {"x": 588, "y": 1078, "width": 224, "height": 286}, {"x": 586, "y": 1078, "width": 224, "height": 286}, {"x": 588, "y": 1080, "width": 224, "height": 286}, {"x": 588, "y": 1080, "width": 224, "height": 286}, {"x": 588, "y": 1080, "width": 224, "height": 286}, {"x": 588, "y": 1080, "width": 224, "height": 286}, {"x": 588, "y": 1082, "width": 224, "height": 286}, {"x": 592, "y": 1086, "width": 220, "height": 280}, {"x": 590, "y": 1086, "width": 220, "height": 280}, {"x": 590, "y": 1084, "width": 220, "height": 280}, {"x": 590, "y": 1086, "width": 220, "height": 280}, {"x": 590, "y": 1086, "width": 220, "height": 280}, {"x": 590, "y": 1086, "width": 220, "height": 280}, {"x": 588, "y": 1084, "width": 224, "height": 286}, {"x": 588, "y": 1084, "width": 224, "height": 286}, {"x": 588, "y": 1084, "width": 224, "height": 286}, {"x": 588, "y": 1084, "width": 224, "height": 286}, {"x": 590, "y": 1084, "width": 224, "height": 286}, {"x": 588, "y": 1084, "width": 224, "height": 286}, {"x": 588, "y": 1082, "width": 224, "height": 286}, {"x": 590, "y": 1080, "width": 224, "height": 286}, {"x": 588, "y": 1080, "width": 224, "height": 286}, {"x": 588, "y": 1078, "width": 224, "height": 286}, {"x": 590, "y": 1078, "width": 224, "height": 286}, {"x": 588, "y": 1076, "width": 224, "height": 286}, {"x": 588, "y": 1076, "width": 224, "height": 286}, {"x": 588, "y": 1076, "width": 224, "height": 286}, {"x": 588, "y": 1074, "width": 224, "height": 286}, {"x": 588, "y": 1074, "width": 224, "height": 286}, {"x": 588, "y": 1076, "width": 224, "height": 286}, {"x": 588, "y": 1074, "width": 224, "height": 286}, {"x": 588, "y": 1074, "width": 224, "height": 286}, {"x": 588, "y": 1074, "width": 224, "height": 286}, {"x": 588, "y": 1076, "width": 224, "height": 286}, {"x": 588, "y": 1076, "width": 224, "height": 286}, {"x": 588, "y": 1076, "width": 224, "height": 286}, {"x": 590, "y": 1078, "width": 220, "height": 280}, {"x": 592, "y": 1078, "width": 220, "height": 280}, {"x": 592, "y": 1078, "width": 220, "height": 280}, {"x": 592, "y": 1078, "width": 220, "height": 280}, {"x": 592, "y": 1078, "width": 220, "height": 280}, {"x": 592, "y": 1078, "width": 220, "height": 280}, {"x": 592, "y": 1078, "width": 220, "height": 280}, {"x": 594, "y": 1080, "width": 216, "height": 274}, {"x": 592, "y": 1080, "width": 216, "height": 274}, {"x": 590, "y": 1078, "width": 220, "height": 280}, {"x": 592, "y": 1078, "width": 220, "height": 280}, {"x": 590, "y": 1078, "width": 220, "height": 280}, {"x": 592, "y": 1078, "width": 220, "height": 280}, {"x": 590, "y": 1076, "width": 220, "height": 280}, {"x": 590, "y": 1078, "width": 220, "height": 280}, {"x": 590, "y": 1078, "width": 220, "height": 280}, {"x": 590, "y": 1078, "width": 220, "height": 280}, {"x": 590, "y": 1078, "width": 220, "height": 280}, {"x": 588, "y": 1076, "width": 224, "height": 286}, {"x": 590, "y": 1078, "width": 220, "height": 280}, {"x": 590, "y": 1078, "width": 220, "height": 280}, {"x": 590, "y": 1078, "width": 220, "height": 280}, {"x": 590, "y": 1078, "width": 220, "height": 280}, {"x": 590, "y": 1078, "width": 220, "height": 280}, {"x": 590, "y": 1078, "width": 220, "height": 280}, {"x": 590, "y": 1080, "width": 220, "height": 280}, {"x": 590, "y": 1080, "width": 220, "height": 280}, {"x": 588, "y": 1080, "width": 220, "height": 280}, {"x": 588, "y": 1080, "width": 220, "height": 280}, {"x": 588, "y": 1078, "width": 220, "height": 280}, {"x": 588, "y": 1080, "width": 220, "height": 280}, {"x": 588, "y": 1080, "width": 220, "height": 280}, {"x": 588, "y": 1080, "width": 220, "height": 280}, {"x": 590, "y": 1082, "width": 220, "height": 280}, {"x": 588, "y": 1080, "width": 220, "height": 280}, {"x": 588, "y": 1080, "width": 220, "height": 280}, {"x": 588, "y": 1080, "width": 220, "height": 280}, {"x": 588, "y": 1080, "width": 220, "height": 280}, {"x": 588, "y": 1082, "width": 220, "height": 280}, {"x": 588, "y": 1082, "width": 220, "height": 280}, {"x": 588, "y": 1082, "width": 220, "height": 280}, {"x": 588, "y": 1080, "width": 220, "height": 280}, {"x": 588, "y": 1080, "width": 220, "height": 280}, {"x": 586, "y": 1080, "width": 220, "height": 280}, {"x": 586, "y": 1080, "width": 220, "height": 280}, {"x": 588, "y": 1080, "width": 220, "height": 280}, {"x": 588, "y": 1078, "width": 220, "height": 280}, {"x": 588, "y": 1080, "width": 220, "height": 280}, {"x": 588, "y": 1078, "width": 220, "height": 280}, {"x": 590, "y": 1080, "width": 216, "height": 274}, {"x": 590, "y": 1080, "width": 216, "height": 274}, {"x": 590, "y": 1080, "width": 216, "height": 274}, {"x": 590, "y": 1080, "width": 216, "height": 274}, {"x": 588, "y": 1078, "width": 216, "height": 274}, {"x": 588, "y": 1078, "width": 216, "height": 274}, {"x": 588, "y": 1076, "width": 216, "height": 274}, {"x": 588, "y": 1076, "width": 216, "height": 274}, {"x": 592, "y": 1080, "width": 212, "height": 270}, {"x": 592, "y": 1080, "width": 212, "height": 270}, {"x": 594, "y": 1084, "width": 208, "height": 264}, {"x": 594, "y": 1084, "width": 208, "height": 264}, {"x": 596, "y": 1084, "width": 208, "height": 264}, {"x": 596, "y": 1084, "width": 208, "height": 264}, {"x": 594, "y": 1084, "width": 208, "height": 264}, {"x": 596, "y": 1084, "width": 208, "height": 264}, {"x": 596, "y": 1086, "width": 204, "height": 258}, {"x": 594, "y": 1086, "width": 204, "height": 258}, {"x": 596, "y": 1088, "width": 200, "height": 254}, {"x": 598, "y": 1090, "width": 200, "height": 254}, {"x": 598, "y": 1090, "width": 196, "height": 248}, {"x": 598, "y": 1090, "width": 196, "height": 248}, {"x": 598, "y": 1090, "width": 196, "height": 248}, {"x": 598, "y": 1090, "width": 196, "height": 248}, {"x": 598, "y": 1092, "width": 196, "height": 248}, {"x": 598, "y": 1090, "width": 200, "height": 254}, {"x": 598, "y": 1090, "width": 200, "height": 254}, {"x": 598, "y": 1090, "width": 200, "height": 254}, {"x": 598, "y": 1088, "width": 204, "height": 258}, {"x": 596, "y": 1088, "width": 204, "height": 258}, {"x": 596, "y": 1088, "width": 204, "height": 258}, {"x": 596, "y": 1088, "width": 204, "height": 258}, {"x": 598, "y": 1090, "width": 200, "height": 254}, {"x": 598, "y": 1092, "width": 204, "height": 258}, {"x": 596, "y": 1088, "width": 204, "height": 258}, {"x": 596, "y": 1090, "width": 204, "height": 258}, {"x": 596, "y": 1090, "width": 204, "height": 258}, {"x": 594, "y": 1088, "width": 208, "height": 264}, {"x": 594, "y": 1088, "width": 208, "height": 264}, {"x": 596, "y": 1090, "width": 208, "height": 264}, {"x": 594, "y": 1090, "width": 208, "height": 264}, {"x": 596, "y": 1090, "width": 208, "height": 264}, {"x": 592, "y": 1084, "width": 216, "height": 274}, {"x": 592, "y": 1086, "width": 212, "height": 270}, {"x": 592, "y": 1086, "width": 212, "height": 270}, {"x": 592, "y": 1086, "width": 212, "height": 270}, {"x": 592, "y": 1088, "width": 212, "height": 270}, {"x": 590, "y": 1086, "width": 216, "height": 274}, {"x": 590, "y": 1084, "width": 216, "height": 274}, {"x": 590, "y": 1084, "width": 216, "height": 274}, {"x": 592, "y": 1086, "width": 212, "height": 270}, {"x": 592, "y": 1088, "width": 212, "height": 270}, {"x": 592, "y": 1086, "width": 212, "height": 270}, {"x": 592, "y": 1086, "width": 216, "height": 274}, {"x": 590, "y": 1084, "width": 216, "height": 274}, {"x": 592, "y": 1086, "width": 212, "height": 270}, {"x": 594, "y": 1088, "width": 212, "height": 270}, {"x": 592, "y": 1088, "width": 212, "height": 270}, {"x": 592, "y": 1088, "width": 212, "height": 270}, {"x": 590, "y": 1084, "width": 216, "height": 274}, {"x": 590, "y": 1086, "width": 212, "height": 270}, {"x": 592, "y": 1088, "width": 212, "height": 270}, {"x": 592, "y": 1088, "width": 212, "height": 270}, {"x": 592, "y": 1088, "width": 212, "height": 270}, {"x": 592, "y": 1088, "width": 212, "height": 270}, {"x": 592, "y": 1088, "width": 212, "height": 270}, {"x": 592, "y": 1088, "width": 212, "height": 270}, {"x": 592, "y": 1090, "width": 212, "height": 270}, {"x": 592, "y": 1088, "width": 212, "height": 270}, {"x": 590, "y": 1086, "width": 216, "height": 274}, {"x": 590, "y": 1088, "width": 212, "height": 270}, {"x": 592, "y": 1090, "width": 212, "height": 270}, {"x": 592, "y": 1090, "width": 212, "height": 270}, {"x": 592, "y": 1090, "width": 212, "height": 270}, {"x": 592, "y": 1090, "width": 212, "height": 270}, {"x": 592, "y": 1092, "width": 212, "height": 270}, {"x": 590, "y": 1090, "width": 212, "height": 270}, {"x": 590, "y": 1092, "width": 212, "height": 270}, {"x": 590, "y": 1094, "width": 208, "height": 264}, {"x": 590, "y": 1096, "width": 208, "height": 264}, {"x": 592, "y": 1098, "width": 204, "height": 258}, {"x": 590, "y": 1098, "width": 204, "height": 258}, {"x": 588, "y": 1102, "width": 204, "height": 258}, {"x": 586, "y": 1102, "width": 204, "height": 258}, {"x": 584, "y": 1104, "width": 204, "height": 258}, {"x": 582, "y": 1106, "width": 200, "height": 254}, {"x": 584, "y": 1110, "width": 200, "height": 254}, {"x": 584, "y": 1110, "width": 200, "height": 254}, {"x": 586, "y": 1114, "width": 196, "height": 248}, {"x": 588, "y": 1116, "width": 192, "height": 244}, {"x": 590, "y": 1116, "width": 196, "height": 248}, {"x": 588, "y": 1116, "width": 192, "height": 244}, {"x": 588, "y": 1118, "width": 192, "height": 244}, {"x": 586, "y": 1118, "width": 192, "height": 244}, {"x": 584, "y": 1118, "width": 192, "height": 244}, {"x": 582, "y": 1118, "width": 192, "height": 244}, {"x": 584, "y": 1118, "width": 192, "height": 244}, {"x": 584, "y": 1118, "width": 192, "height": 244}, {"x": 584, "y": 1118, "width": 192, "height": 244}, {"x": 586, "y": 1118, "width": 192, "height": 244}, {"x": 584, "y": 1118, "width": 192, "height": 244}, {"x": 586, "y": 1122, "width": 188, "height": 240}, {"x": 582, "y": 1120, "width": 192, "height": 244}, {"x": 584, "y": 1124, "width": 188, "height": 240}, {"x": 584, "y": 1128, "width": 184, "height": 234}, {"x": 584, "y": 1126, "width": 184, "height": 234}, {"x": 580, "y": 1120, "width": 188, "height": 240}, {"x": 582, "y": 1112, "width": 188, "height": 240}, {"x": 584, "y": 1108, "width": 188, "height": 240}, {"x": 592, "y": 1108, "width": 184, "height": 234}, {"x": 594, "y": 1112, "width": 180, "height": 230}, {"x": 590, "y": 1110, "width": 184, "height": 234}, {"x": 586, "y": 1110, "width": 184, "height": 234}, {"x": 584, "y": 1110, "width": 184, "height": 234}, {"x": 580, "y": 1108, "width": 188, "height": 240}, {"x": 578, "y": 1106, "width": 188, "height": 240}, {"x": 584, "y": 1106, "width": 188, "height": 240}, {"x": 586, "y": 1102, "width": 188, "height": 240}, {"x": 588, "y": 1100, "width": 192, "height": 244}, {"x": 588, "y": 1094, "width": 196, "height": 248}, {"x": 588, "y": 1094, "width": 196, "height": 248}, {"x": 588, "y": 1092, "width": 196, "height": 248}, {"x": 582, "y": 1090, "width": 200, "height": 254}, {"x": 582, "y": 1092, "width": 200, "height": 254}, {"x": 584, "y": 1092, "width": 200, "height": 254}, {"x": 582, "y": 1090, "width": 200, "height": 254}, {"x": 584, "y": 1090, "width": 200, "height": 254}, {"x": 586, "y": 1090, "width": 200, "height": 254}, {"x": 586, "y": 1088, "width": 200, "height": 254}, {"x": 588, "y": 1088, "width": 200, "height": 254}, {"x": 588, "y": 1090, "width": 196, "height": 248}, {"x": 586, "y": 1088, "width": 196, "height": 248}, {"x": 584, "y": 1088, "width": 196, "height": 248}, {"x": 586, "y": 1090, "width": 196, "height": 248}, {"x": 586, "y": 1090, "width": 196, "height": 248}, {"x": 588, "y": 1090, "width": 196, "height": 248}, {"x": 588, "y": 1092, "width": 196, "height": 248}, {"x": 588, "y": 1090, "width": 196, "height": 248}, {"x": 588, "y": 1090, "width": 196, "height": 248}, {"x": 588, "y": 1092, "width": 192, "height": 244}, {"x": 588, "y": 1092, "width": 192, "height": 244}, {"x": 584, "y": 1092, "width": 192, "height": 244}, {"x": 584, "y": 1092, "width": 192, "height": 244}, {"x": 586, "y": 1094, "width": 192, "height": 244}, {"x": 586, "y": 1092, "width": 192, "height": 244}, {"x": 588, "y": 1092, "width": 192, "height": 244}, {"x": 590, "y": 1094, "width": 188, "height": 240}, {"x": 592, "y": 1096, "width": 184, "height": 234}, {"x": 590, "y": 1094, "width": 184, "height": 234}, {"x": 590, "y": 1096, "width": 184, "height": 234}, {"x": 590, "y": 1100, "width": 180, "height": 230}, {"x": 590, "y": 1100, "width": 180, "height": 230}, {"x": 592, "y": 1100, "width": 180, "height": 230}, {"x": 594, "y": 1104, "width": 180, "height": 230}, {"x": 594, "y": 1104, "width": 180, "height": 230}, {"x": 594, "y": 1104, "width": 180, "height": 230}, {"x": 594, "y": 1108, "width": 180, "height": 230}, {"x": 592, "y": 1108, "width": 184, "height": 234}, {"x": 590, "y": 1110, "width": 184, "height": 234}, {"x": 590, "y": 1114, "width": 180, "height": 230}, {"x": 588, "y": 1114, "width": 180, "height": 230}, {"x": 588, "y": 1116, "width": 180, "height": 230}, {"x": 590, "y": 1118, "width": 180, "height": 230}, {"x": 590, "y": 1118, "width": 180, "height": 230}, {"x": 594, "y": 1120, "width": 180, "height": 230}, {"x": 594, "y": 1120, "width": 180, "height": 230}, {"x": 594, "y": 1118, "width": 180, "height": 230}, {"x": 594, "y": 1120, "width": 180, "height": 230}, {"x": 594, "y": 1120, "width": 180, "height": 230}, {"x": 592, "y": 1118, "width": 180, "height": 230}, {"x": 592, "y": 1120, "width": 180, "height": 230}, {"x": 592, "y": 1118, "width": 180, "height": 230}, {"x": 592, "y": 1120, "width": 180, "height": 230}, {"x": 592, "y": 1118, "width": 180, "height": 230}, {"x": 594, "y": 1120, "width": 180, "height": 230}, {"x": 592, "y": 1118, "width": 180, "height": 230}, {"x": 594, "y": 1120, "width": 180, "height": 230}, {"x": 594, "y": 1120, "width": 180, "height": 230}, {"x": 592, "y": 1120, "width": 180, "height": 230}, {"x": 594, "y": 1120, "width": 180, "height": 230}, {"x": 594, "y": 1120, "width": 180, "height": 230}, {"x": 594, "y": 1120, "width": 180, "height": 230}, {"x": 594, "y": 1120, "width": 180, "height": 230}, {"x": 594, "y": 1120, "width": 180, "height": 230}, {"x": 596, "y": 1122, "width": 180, "height": 230}, {"x": 594, "y": 1120, "width": 180, "height": 230}, {"x": 594, "y": 1120, "width": 180, "height": 230}, {"x": 596, "y": 1120, "width": 180, "height": 230}, {"x": 596, "y": 1120, "width": 180, "height": 230}, {"x": 596, "y": 1118, "width": 180, "height": 230}, {"x": 596, "y": 1120, "width": 180, "height": 230}, {"x": 594, "y": 1120, "width": 180, "height": 230}, {"x": 596, "y": 1120, "width": 180, "height": 230}, {"x": 594, "y": 1118, "width": 180, "height": 230}, {"x": 596, "y": 1120, "width": 180, "height": 230}, {"x": 596, "y": 1120, "width": 180, "height": 230}, {"x": 596, "y": 1118, "width": 180, "height": 230}, {"x": 596, "y": 1120, "width": 180, "height": 230}, {"x": 594, "y": 1118, "width": 180, "height": 230}, {"x": 596, "y": 1120, "width": 180, "height": 230}, {"x": 594, "y": 1118, "width": 180, "height": 230}, {"x": 596, "y": 1118, "width": 180, "height": 230}, {"x": 594, "y": 1118, "width": 180, "height": 230}, {"x": 596, "y": 1120, "width": 180, "height": 230}, {"x": 594, "y": 1118, "width": 180, "height": 230}, {"x": 596, "y": 1118, "width": 180, "height": 230}, {"x": 596, "y": 1118, "width": 180, "height": 230}, {"x": 596, "y": 1118, "width": 180, "height": 230}, {"x": 596, "y": 1118, "width": 180, "height": 230}, {"x": 596, "y": 1118, "width": 180, "height": 230}, {"x": 596, "y": 1118, "width": 180, "height": 230}, {"x": 596, "y": 1118, "width": 180, "height": 230}, {"x": 596, "y": 1118, "width": 180, "height": 230}, {"x": 596, "y": 1118, "width": 180, "height": 230}, {"x": 594, "y": 1118, "width": 180, "height": 230}, {"x": 592, "y": 1116, "width": 184, "height": 234}, {"x": 592, "y": 1116, "width": 184, "height": 234}, {"x": 592, "y": 1116, "width": 184, "height": 234}, {"x": 594, "y": 1116, "width": 184, "height": 234}, {"x": 594, "y": 1116, "width": 184, "height": 234}, {"x": 592, "y": 1116, "width": 184, "height": 234}, {"x": 592, "y": 1116, "width": 184, "height": 234}, {"x": 594, "y": 1116, "width": 184, "height": 234}, {"x": 594, "y": 1116, "width": 184, "height": 234}, {"x": 594, "y": 1116, "width": 184, "height": 234}, {"x": 594, "y": 1116, "width": 184, "height": 234}, {"x": 592, "y": 1114, "width": 184, "height": 234}, {"x": 592, "y": 1114, "width": 184, "height": 234}, {"x": 594, "y": 1116, "width": 184, "height": 234}, {"x": 592, "y": 1114, "width": 184, "height": 234}, {"x": 594, "y": 1116, "width": 184, "height": 234}, {"x": 594, "y": 1114, "width": 184, "height": 234}, {"x": 594, "y": 1116, "width": 184, "height": 234}, {"x": 592, "y": 1116, "width": 184, "height": 234}, {"x": 592, "y": 1114, "width": 184, "height": 234}, {"x": 594, "y": 1118, "width": 180, "height": 230}, {"x": 594, "y": 1116, "width": 180, "height": 230}, {"x": 596, "y": 1116, "width": 180, "height": 230}, {"x": 596, "y": 1116, "width": 180, "height": 230}, {"x": 596, "y": 1116, "width": 180, "height": 230}, {"x": 594, "y": 1112, "width": 184, "height": 234}, {"x": 594, "y": 1114, "width": 184, "height": 234}, {"x": 594, "y": 1114, "width": 180, "height": 230}, {"x": 594, "y": 1116, "width": 180, "height": 230}, {"x": 596, "y": 1116, "width": 178, "height": 226}, {"x": 596, "y": 1116, "width": 178, "height": 226}, {"x": 596, "y": 1118, "width": 178, "height": 226}, {"x": 596, "y": 1118, "width": 178, "height": 226}, {"x": 596, "y": 1118, "width": 178, "height": 226}, {"x": 594, "y": 1118, "width": 178, "height": 226}, {"x": 596, "y": 1118, "width": 178, "height": 226}, {"x": 594, "y": 1118, "width": 178, "height": 226}, {"x": 594, "y": 1116, "width": 180, "height": 230}, {"x": 596, "y": 1122, "width": 178, "height": 226}, {"x": 594, "y": 1126, "width": 178, "height": 226}, {"x": 596, "y": 1132, "width": 174, "height": 220}, {"x": 594, "y": 1132, "width": 174, "height": 220}, {"x": 596, "y": 1134, "width": 170, "height": 216}, {"x": 598, "y": 1136, "width": 170, "height": 216}, {"x": 600, "y": 1138, "width": 170, "height": 216}, {"x": 598, "y": 1136, "width": 170, "height": 216}, {"x": 600, "y": 1136, "width": 170, "height": 216}, {"x": 602, "y": 1136, "width": 168, "height": 212}, {"x": 600, "y": 1134, "width": 170, "height": 216}, {"x": 598, "y": 1132, "width": 170, "height": 216}, {"x": 600, "y": 1134, "width": 170, "height": 216}, {"x": 596, "y": 1130, "width": 174, "height": 220}, {"x": 598, "y": 1132, "width": 174, "height": 220}, {"x": 594, "y": 1130, "width": 178, "height": 226}, {"x": 596, "y": 1130, "width": 178, "height": 226}, {"x": 596, "y": 1132, "width": 178, "height": 226}, {"x": 596, "y": 1132, "width": 178, "height": 226}, {"x": 596, "y": 1132, "width": 178, "height": 226}, {"x": 594, "y": 1130, "width": 178, "height": 226}, {"x": 594, "y": 1132, "width": 178, "height": 226}, {"x": 594, "y": 1132, "width": 178, "height": 226}, {"x": 594, "y": 1132, "width": 178, "height": 226}, {"x": 596, "y": 1134, "width": 174, "height": 220}, {"x": 596, "y": 1132, "width": 174, "height": 220}, {"x": 598, "y": 1134, "width": 174, "height": 220}, {"x": 596, "y": 1134, "width": 174, "height": 220}, {"x": 596, "y": 1134, "width": 174, "height": 220}, {"x": 596, "y": 1132, "width": 174, "height": 220}, {"x": 594, "y": 1130, "width": 178, "height": 226}, {"x": 594, "y": 1130, "width": 178, "height": 226}, {"x": 594, "y": 1132, "width": 178, "height": 226}, {"x": 596, "y": 1132, "width": 178, "height": 226}, {"x": 594, "y": 1130, "width": 178, "height": 226}, {"x": 594, "y": 1130, "width": 178, "height": 226}, {"x": 594, "y": 1130, "width": 178, "height": 226}, {"x": 594, "y": 1130, "width": 178, "height": 226}, {"x": 594, "y": 1130, "width": 178, "height": 226}, {"x": 594, "y": 1130, "width": 178, "height": 226}, {"x": 594, "y": 1130, "width": 178, "height": 226}, {"x": 594, "y": 1130, "width": 178, "height": 226}, {"x": 594, "y": 1130, "width": 178, "height": 226}, {"x": 594, "y": 1130, "width": 178, "height": 226}, {"x": 594, "y": 1130, "width": 178, "height": 226}, {"x": 594, "y": 1130, "width": 178, "height": 226}, {"x": 594, "y": 1130, "width": 178, "height": 226}, {"x": 594, "y": 1130, "width": 178, "height": 226}, {"x": 594, "y": 1130, "width": 178, "height": 226}, {"x": 594, "y": 1130, "width": 178, "height": 226}, {"x": 594, "y": 1130, "width": 178, "height": 226}, {"x": 594, "y": 1130, "width": 178, "height": 226}, {"x": 594, "y": 1130, "width": 178, "height": 226}, {"x": 594, "y": 1130, "width": 178, "height": 226}, {"x": 594, "y": 1130, "width": 178, "height": 226}, {"x": 594, "y": 1130, "width": 178, "height": 226}, {"x": 594, "y": 1130, "width": 178, "height": 226}, {"x": 594, "y": 1130, "width": 178, "height": 226}, {"x": 592, "y": 1126, "width": 180, "height": 230}, {"x": 594, "y": 1130, "width": 178, "height": 226}, {"x": 594, "y": 1130, "width": 178, "height": 226}, {"x": 596, "y": 1130, "width": 178, "height": 226}, {"x": 596, "y": 1130, "width": 178, "height": 226}, {"x": 596, "y": 1130, "width": 178, "height": 226}, {"x": 594, "y": 1128, "width": 178, "height": 226}, {"x": 596, "y": 1128, "width": 178, "height": 226}, {"x": 596, "y": 1130, "width": 178, "height": 226}, {"x": 594, "y": 1128, "width": 178, "height": 226}, {"x": 594, "y": 1128, "width": 178, "height": 226}, {"x": 594, "y": 1128, "width": 178, "height": 226}, {"x": 594, "y": 1128, "width": 178, "height": 226}, {"x": 594, "y": 1128, "width": 178, "height": 226}, {"x": 594, "y": 1128, "width": 178, "height": 226}, {"x": 594, "y": 1128, "width": 178, "height": 226}, {"x": 594, "y": 1128, "width": 178, "height": 226}, {"x": 594, "y": 1128, "width": 178, "height": 226}, {"x": 594, "y": 1130, "width": 178, "height": 226}, {"x": 594, "y": 1130, "width": 178, "height": 226}, {"x": 594, "y": 1128, "width": 178, "height": 226}, {"x": 592, "y": 1128, "width": 178, "height": 226}, {"x": 594, "y": 1128, "width": 178, "height": 226}, {"x": 594, "y": 1128, "width": 178, "height": 226}, {"x": 594, "y": 1128, "width": 178, "height": 226}, {"x": 594, "y": 1128, "width": 178, "height": 226}, {"x": 594, "y": 1128, "width": 178, "height": 226}, {"x": 596, "y": 1128, "width": 178, "height": 226}, {"x": 594, "y": 1128, "width": 178, "height": 226}, {"x": 594, "y": 1128, "width": 178, "height": 226}, {"x": 594, "y": 1128, "width": 178, "height": 226}, {"x": 596, "y": 1130, "width": 174, "height": 220}, {"x": 596, "y": 1130, "width": 174, "height": 220}, {"x": 594, "y": 1128, "width": 178, "height": 226}, {"x": 594, "y": 1128, "width": 178, "height": 226}, {"x": 594, "y": 1128, "width": 178, "height": 226}, {"x": 594, "y": 1128, "width": 178, "height": 226}, {"x": 596, "y": 1128, "width": 178, "height": 226}, {"x": 596, "y": 1128, "width": 178, "height": 226}, {"x": 594, "y": 1126, "width": 178, "height": 226}, {"x": 596, "y": 1128, "width": 178, "height": 226}, {"x": 598, "y": 1130, "width": 174, "height": 220}, {"x": 598, "y": 1128, "width": 174, "height": 220}, {"x": 596, "y": 1128, "width": 178, "height": 226}, {"x": 596, "y": 1128, "width": 178, "height": 226}, {"x": 596, "y": 1128, "width": 178, "height": 226}, {"x": 596, "y": 1128, "width": 178, "height": 226}, {"x": 596, "y": 1128, "width": 178, "height": 226}, {"x": 596, "y": 1130, "width": 178, "height": 226}, {"x": 596, "y": 1130, "width": 178, "height": 226}, {"x": 596, "y": 1128, "width": 178, "height": 226}, {"x": 596, "y": 1130, "width": 178, "height": 226}, {"x": 596, "y": 1130, "width": 178, "height": 226}, {"x": 596, "y": 1130, "width": 178, "height": 226}, {"x": 596, "y": 1130, "width": 178, "height": 226}, {"x": 598, "y": 1132, "width": 174, "height": 220}, {"x": 598, "y": 1132, "width": 174, "height": 220}, {"x": 598, "y": 1132, "width": 174, "height": 220}, {"x": 598, "y": 1132, "width": 174, "height": 220}, {"x": 598, "y": 1132, "width": 174, "height": 220}, {"x": 596, "y": 1132, "width": 174, "height": 220}, {"x": 598, "y": 1132, "width": 174, "height": 220}, {"x": 596, "y": 1130, "width": 178, "height": 226}, {"x": 596, "y": 1130, "width": 178, "height": 226}, {"x": 598, "y": 1132, "width": 178, "height": 226}, {"x": 596, "y": 1132, "width": 178, "height": 226}, {"x": 596, "y": 1132, "width": 178, "height": 226}, {"x": 596, "y": 1130, "width": 178, "height": 226}, {"x": 596, "y": 1132, "width": 178, "height": 226}, {"x": 596, "y": 1130, "width": 178, "height": 226}, {"x": 596, "y": 1130, "width": 178, "height": 226}, {"x": 596, "y": 1132, "width": 178, "height": 226}, {"x": 596, "y": 1132, "width": 178, "height": 226}, {"x": 596, "y": 1130, "width": 178, "height": 226}, {"x": 596, "y": 1132, "width": 178, "height": 226}, {"x": 596, "y": 1132, "width": 178, "height": 226}, {"x": 594, "y": 1132, "width": 178, "height": 226}, {"x": 596, "y": 1132, "width": 178, "height": 226}, {"x": 594, "y": 1132, "width": 178, "height": 226}, {"x": 596, "y": 1132, "width": 178, "height": 226}, {"x": 596, "y": 1130, "width": 178, "height": 226}, {"x": 596, "y": 1132, "width": 178, "height": 226}, {"x": 596, "y": 1132, "width": 178, "height": 226}, {"x": 596, "y": 1132, "width": 178, "height": 226}, {"x": 596, "y": 1132, "width": 178, "height": 226}, {"x": 596, "y": 1130, "width": 178, "height": 226}, {"x": 596, "y": 1132, "width": 178, "height": 226}, {"x": 594, "y": 1130, "width": 178, "height": 226}, {"x": 596, "y": 1132, "width": 178, "height": 226}, {"x": 596, "y": 1132, "width": 178, "height": 226}, {"x": 596, "y": 1130, "width": 178, "height": 226}, {"x": 596, "y": 1132, "width": 178, "height": 226}, {"x": 596, "y": 1132, "width": 178, "height": 226}, {"x": 596, "y": 1132, "width": 178, "height": 226}, {"x": 596, "y": 1132, "width": 178, "height": 226}, {"x": 594, "y": 1130, "width": 178, "height": 226}, {"x": 596, "y": 1130, "width": 178, "height": 226}, {"x": 596, "y": 1130, "width": 178, "height": 226}, {"x": 596, "y": 1130, "width": 178, "height": 226}, {"x": 596, "y": 1130, "width": 178, "height": 226}, {"x": 596, "y": 1130, "width": 178, "height": 226}, {"x": 594, "y": 1130, "width": 178, "height": 226}, {"x": 596, "y": 1130, "width": 178, "height": 226}, {"x": 596, "y": 1130, "width": 178, "height": 226}, {"x": 596, "y": 1130, "width": 178, "height": 226}, {"x": 594, "y": 1130, "width": 178, "height": 226}, {"x": 594, "y": 1130, "width": 178, "height": 226}, {"x": 594, "y": 1130, "width": 178, "height": 226}, {"x": 594, "y": 1130, "width": 178, "height": 226}, {"x": 594, "y": 1130, "width": 178, "height": 226}, {"x": 594, "y": 1130, "width": 178, "height": 226}, {"x": 594, "y": 1130, "width": 178, "height": 226}, {"x": 594, "y": 1130, "width": 178, "height": 226}, {"x": 596, "y": 1130, "width": 178, "height": 226}, {"x": 596, "y": 1130, "width": 178, "height": 226}, {"x": 594, "y": 1128, "width": 178, "height": 226}, {"x": 596, "y": 1128, "width": 178, "height": 226}, {"x": 594, "y": 1128, "width": 178, "height": 226}, {"x": 594, "y": 1128, "width": 178, "height": 226}, {"x": 596, "y": 1128, "width": 178, "height": 226}, {"x": 596, "y": 1128, "width": 178, "height": 226}, {"x": 594, "y": 1128, "width": 178, "height": 226}, {"x": 596, "y": 1128, "width": 178, "height": 226}, {"x": 594, "y": 1128, "width": 178, "height": 226}, {"x": 594, "y": 1128, "width": 178, "height": 226}, {"x": 594, "y": 1128, "width": 178, "height": 226}, {"x": 594, "y": 1128, "width": 178, "height": 226}, {"x": 592, "y": 1126, "width": 180, "height": 230}, {"x": 594, "y": 1128, "width": 178, "height": 226}, {"x": 594, "y": 1128, "width": 178, "height": 226}, {"x": 596, "y": 1130, "width": 178, "height": 226}, {"x": 594, "y": 1128, "width": 178, "height": 226}, {"x": 596, "y": 1130, "width": 178, "height": 226}, {"x": 594, "y": 1130, "width": 178, "height": 226}, {"x": 594, "y": 1128, "width": 178, "height": 226}, {"x": 594, "y": 1130, "width": 178, "height": 226}, {"x": 594, "y": 1128, "width": 178, "height": 226}, {"x": 596, "y": 1128, "width": 178, "height": 226}, {"x": 598, "y": 1132, "width": 174, "height": 220}, {"x": 596, "y": 1130, "width": 174, "height": 220}, {"x": 596, "y": 1132, "width": 174, "height": 220}, {"x": 598, "y": 1132, "width": 174, "height": 220}, {"x": 594, "y": 1128, "width": 178, "height": 226}, {"x": 596, "y": 1130, "width": 178, "height": 226}, {"x": 596, "y": 1128, "width": 178, "height": 226}, {"x": 596, "y": 1130, "width": 178, "height": 226}, {"x": 596, "y": 1130, "width": 178, "height": 226}, {"x": 596, "y": 1130, "width": 178, "height": 226}, {"x": 594, "y": 1128, "width": 178, "height": 226}, {"x": 596, "y": 1128, "width": 178, "height": 226}, {"x": 596, "y": 1130, "width": 178, "height": 226}, {"x": 596, "y": 1130, "width": 178, "height": 226}, {"x": 596, "y": 1130, "width": 178, "height": 226}, {"x": 596, "y": 1130, "width": 178, "height": 226}, {"x": 594, "y": 1130, "width": 178, "height": 226}, {"x": 596, "y": 1130, "width": 178, "height": 226}, {"x": 596, "y": 1132, "width": 178, "height": 226}, {"x": 594, "y": 1130, "width": 178, "height": 226}, {"x": 594, "y": 1132, "width": 178, "height": 226}, {"x": 596, "y": 1132, "width": 178, "height": 226}, {"x": 594, "y": 1130, "width": 178, "height": 226}, {"x": 596, "y": 1130, "width": 178, "height": 226}, {"x": 594, "y": 1130, "width": 178, "height": 226}, {"x": 594, "y": 1132, "width": 178, "height": 226}, {"x": 596, "y": 1132, "width": 178, "height": 226}, {"x": 594, "y": 1130, "width": 178, "height": 226}, {"x": 596, "y": 1130, "width": 178, "height": 226}, {"x": 596, "y": 1130, "width": 178, "height": 226}, {"x": 596, "y": 1132, "width": 178, "height": 226}, {"x": 596, "y": 1132, "width": 178, "height": 226}, {"x": 596, "y": 1132, "width": 178, "height": 226}, {"x": 596, "y": 1130, "width": 178, "height": 226}, {"x": 596, "y": 1132, "width": 178, "height": 226}, {"x": 596, "y": 1132, "width": 178, "height": 226}, {"x": 596, "y": 1130, "width": 178, "height": 226}, {"x": 596, "y": 1132, "width": 178, "height": 226}, {"x": 596, "y": 1132, "width": 178, "height": 226}, {"x": 596, "y": 1132, "width": 178, "height": 226}, {"x": 596, "y": 1132, "width": 178, "height": 226}, {"x": 594, "y": 1132, "width": 178, "height": 226}, {"x": 596, "y": 1130, "width": 178, "height": 226}, {"x": 598, "y": 1134, "width": 174, "height": 220}, {"x": 596, "y": 1130, "width": 178, "height": 226}, {"x": 596, "y": 1132, "width": 178, "height": 226}, {"x": 594, "y": 1132, "width": 178, "height": 226}, {"x": 596, "y": 1130, "width": 178, "height": 226}, {"x": 596, "y": 1132, "width": 178, "height": 226}, {"x": 594, "y": 1130, "width": 178, "height": 226}, {"x": 594, "y": 1130, "width": 178, "height": 226}, {"x": 594, "y": 1130, "width": 178, "height": 226}, {"x": 594, "y": 1130, "width": 178, "height": 226}, {"x": 594, "y": 1130, "width": 178, "height": 226}, {"x": 596, "y": 1130, "width": 178, "height": 226}, {"x": 596, "y": 1128, "width": 178, "height": 226}, {"x": 596, "y": 1126, "width": 178, "height": 226}, {"x": 598, "y": 1128, "width": 174, "height": 220}, {"x": 598, "y": 1126, "width": 178, "height": 226}, {"x": 596, "y": 1124, "width": 178, "height": 226}, {"x": 596, "y": 1124, "width": 178, "height": 226}, {"x": 594, "y": 1122, "width": 178, "height": 226}, {"x": 594, "y": 1126, "width": 174, "height": 220}, {"x": 592, "y": 1126, "width": 174, "height": 220}, {"x": 592, "y": 1124, "width": 174, "height": 220}, {"x": 594, "y": 1126, "width": 174, "height": 220}, {"x": 592, "y": 1126, "width": 174, "height": 220}, {"x": 596, "y": 1128, "width": 174, "height": 220}, {"x": 596, "y": 1128, "width": 174, "height": 220}, {"x": 598, "y": 1128, "width": 174, "height": 220}, {"x": 598, "y": 1128, "width": 174, "height": 220}, {"x": 600, "y": 1128, "width": 174, "height": 220}, {"x": 600, "y": 1128, "width": 174, "height": 220}, {"x": 598, "y": 1128, "width": 174, "height": 220}, {"x": 600, "y": 1128, "width": 174, "height": 220}, {"x": 598, "y": 1128, "width": 174, "height": 220}, {"x": 598, "y": 1126, "width": 174, "height": 220}, {"x": 596, "y": 1122, "width": 174, "height": 220}, {"x": 596, "y": 1120, "width": 174, "height": 220}, {"x": 596, "y": 1118, "width": 174, "height": 220}, {"x": 592, "y": 1114, "width": 178, "height": 226}, {"x": 590, "y": 1112, "width": 178, "height": 226}, {"x": 594, "y": 1112, "width": 174, "height": 220}, {"x": 592, "y": 1110, "width": 178, "height": 226}, {"x": 592, "y": 1112, "width": 178, "height": 226}, {"x": 592, "y": 1112, "width": 178, "height": 226}, {"x": 592, "y": 1114, "width": 178, "height": 226}, {"x": 592, "y": 1116, "width": 178, "height": 226}, {"x": 592, "y": 1116, "width": 178, "height": 226}, {"x": 592, "y": 1116, "width": 178, "height": 226}, {"x": 592, "y": 1116, "width": 178, "height": 226}, {"x": 592, "y": 1116, "width": 178, "height": 226}, {"x": 592, "y": 1114, "width": 180, "height": 230}, {"x": 590, "y": 1114, "width": 184, "height": 234}, {"x": 590, "y": 1112, "width": 184, "height": 234}, {"x": 592, "y": 1114, "width": 184, "height": 234}, {"x": 592, "y": 1114, "width": 184, "height": 234}, {"x": 590, "y": 1114, "width": 184, "height": 234}, {"x": 590, "y": 1114, "width": 184, "height": 234}, {"x": 590, "y": 1114, "width": 184, "height": 234}, {"x": 588, "y": 1112, "width": 188, "height": 240}, {"x": 590, "y": 1116, "width": 184, "height": 234}, {"x": 588, "y": 1114, "width": 184, "height": 234}, {"x": 592, "y": 1118, "width": 180, "height": 230}, {"x": 594, "y": 1118, "width": 180, "height": 230}, {"x": 592, "y": 1118, "width": 180, "height": 230}, {"x": 592, "y": 1116, "width": 180, "height": 230}, {"x": 592, "y": 1118, "width": 180, "height": 230}, {"x": 592, "y": 1116, "width": 180, "height": 230}, {"x": 592, "y": 1118, "width": 180, "height": 230}, {"x": 592, "y": 1118, "width": 180, "height": 230}, {"x": 592, "y": 1116, "width": 180, "height": 230}, {"x": 592, "y": 1116, "width": 180, "height": 230}, {"x": 592, "y": 1116, "width": 180, "height": 230}, {"x": 592, "y": 1116, "width": 180, "height": 230}, {"x": 592, "y": 1116, "width": 180, "height": 230}, {"x": 592, "y": 1116, "width": 180, "height": 230}, {"x": 592, "y": 1116, "width": 180, "height": 230}, {"x": 590, "y": 1116, "width": 180, "height": 230}, {"x": 592, "y": 1116, "width": 180, "height": 230}, {"x": 592, "y": 1116, "width": 180, "height": 230}, {"x": 590, "y": 1116, "width": 180, "height": 230}, {"x": 590, "y": 1114, "width": 180, "height": 230}, {"x": 590, "y": 1116, "width": 180, "height": 230}, {"x": 590, "y": 1114, "width": 180, "height": 230}, {"x": 590, "y": 1114, "width": 180, "height": 230}, {"x": 592, "y": 1116, "width": 178, "height": 226}, {"x": 590, "y": 1114, "width": 178, "height": 226}, {"x": 590, "y": 1116, "width": 178, "height": 226}, {"x": 590, "y": 1116, "width": 178, "height": 226}, {"x": 588, "y": 1114, "width": 178, "height": 226}, {"x": 588, "y": 1116, "width": 178, "height": 226}, {"x": 588, "y": 1116, "width": 178, "height": 226}, {"x": 590, "y": 1116, "width": 178, "height": 226}, {"x": 588, "y": 1114, "width": 178, "height": 226}, {"x": 588, "y": 1114, "width": 178, "height": 226}, {"x": 588, "y": 1114, "width": 178, "height": 226}, {"x": 588, "y": 1114, "width": 178, "height": 226}, {"x": 586, "y": 1112, "width": 180, "height": 230}, {"x": 586, "y": 1112, "width": 180, "height": 230}, {"x": 590, "y": 1116, "width": 178, "height": 226}, {"x": 590, "y": 1116, "width": 178, "height": 226}, {"x": 588, "y": 1114, "width": 178, "height": 226}, {"x": 588, "y": 1116, "width": 178, "height": 226}, {"x": 588, "y": 1114, "width": 178, "height": 226}, {"x": 588, "y": 1116, "width": 178, "height": 226}, {"x": 590, "y": 1118, "width": 174, "height": 220}, {"x": 590, "y": 1118, "width": 174, "height": 220}, {"x": 590, "y": 1118, "width": 174, "height": 220}, {"x": 588, "y": 1118, "width": 174, "height": 220}, {"x": 588, "y": 1118, "width": 174, "height": 220}, {"x": 590, "y": 1120, "width": 174, "height": 220}, {"x": 590, "y": 1118, "width": 174, "height": 220}, {"x": 590, "y": 1118, "width": 174, "height": 220}, {"x": 592, "y": 1120, "width": 174, "height": 220}, {"x": 590, "y": 1118, "width": 178, "height": 226}, {"x": 590, "y": 1118, "width": 178, "height": 226}, {"x": 592, "y": 1118, "width": 178, "height": 226}, {"x": 592, "y": 1118, "width": 178, "height": 226}, {"x": 592, "y": 1116, "width": 180, "height": 230}, {"x": 592, "y": 1118, "width": 180, "height": 230}, {"x": 590, "y": 1120, "width": 180, "height": 230}, {"x": 590, "y": 1120, "width": 180, "height": 230}, {"x": 592, "y": 1122, "width": 178, "height": 226}, {"x": 594, "y": 1122, "width": 178, "height": 226}, {"x": 592, "y": 1122, "width": 178, "height": 226}, {"x": 590, "y": 1120, "width": 180, "height": 230}, {"x": 588, "y": 1120, "width": 180, "height": 230}, {"x": 588, "y": 1120, "width": 180, "height": 230}, {"x": 588, "y": 1120, "width": 180, "height": 230}, {"x": 588, "y": 1122, "width": 180, "height": 230}, {"x": 588, "y": 1120, "width": 180, "height": 230}, {"x": 588, "y": 1120, "width": 180, "height": 230}, {"x": 588, "y": 1120, "width": 180, "height": 230}, {"x": 588, "y": 1120, "width": 180, "height": 230}, {"x": 588, "y": 1118, "width": 180, "height": 230}, {"x": 588, "y": 1118, "width": 180, "height": 230}, {"x": 588, "y": 1118, "width": 180, "height": 230}, {"x": 590, "y": 1120, "width": 178, "height": 226}, {"x": 590, "y": 1120, "width": 178, "height": 226}, {"x": 592, "y": 1120, "width": 178, "height": 226}, {"x": 588, "y": 1118, "width": 180, "height": 230}, {"x": 588, "y": 1118, "width": 180, "height": 230}, {"x": 590, "y": 1118, "width": 180, "height": 230}, {"x": 590, "y": 1118, "width": 180, "height": 230}, {"x": 588, "y": 1118, "width": 180, "height": 230}, {"x": 584, "y": 1116, "width": 184, "height": 234}, {"x": 584, "y": 1114, "width": 188, "height": 240}, {"x": 584, "y": 1114, "width": 188, "height": 240}, {"x": 584, "y": 1114, "width": 188, "height": 240}, {"x": 584, "y": 1114, "width": 184, "height": 234}, {"x": 586, "y": 1116, "width": 184, "height": 234}, {"x": 584, "y": 1112, "width": 184, "height": 234}, {"x": 584, "y": 1112, "width": 184, "height": 234}, {"x": 584, "y": 1112, "width": 184, "height": 234}, {"x": 586, "y": 1114, "width": 180, "height": 230}, {"x": 588, "y": 1116, "width": 178, "height": 226}, {"x": 590, "y": 1114, "width": 178, "height": 226}, {"x": 590, "y": 1114, "width": 178, "height": 226}, {"x": 592, "y": 1114, "width": 178, "height": 226}, {"x": 592, "y": 1112, "width": 178, "height": 226}, {"x": 592, "y": 1110, "width": 178, "height": 226}, {"x": 594, "y": 1110, "width": 178, "height": 226}, {"x": 592, "y": 1108, "width": 180, "height": 230}, {"x": 590, "y": 1108, "width": 180, "height": 230}, {"x": 590, "y": 1108, "width": 180, "height": 230}, {"x": 590, "y": 1108, "width": 180, "height": 230}, {"x": 590, "y": 1108, "width": 180, "height": 230}, {"x": 588, "y": 1108, "width": 180, "height": 230}, {"x": 588, "y": 1108, "width": 180, "height": 230}, {"x": 588, "y": 1112, "width": 178, "height": 226}, {"x": 586, "y": 1112, "width": 178, "height": 226}, {"x": 586, "y": 1114, "width": 178, "height": 226}, {"x": 584, "y": 1112, "width": 178, "height": 226}, {"x": 588, "y": 1116, "width": 174, "height": 220}, {"x": 588, "y": 1118, "width": 170, "height": 216}, {"x": 588, "y": 1118, "width": 170, "height": 216}, {"x": 590, "y": 1122, "width": 168, "height": 212}, {"x": 592, "y": 1122, "width": 168, "height": 212}, {"x": 592, "y": 1122, "width": 168, "height": 212}, {"x": 592, "y": 1124, "width": 168, "height": 212}, {"x": 594, "y": 1124, "width": 168, "height": 212}, {"x": 594, "y": 1126, "width": 164, "height": 208}, {"x": 594, "y": 1126, "width": 164, "height": 208}, {"x": 594, "y": 1124, "width": 168, "height": 212}, {"x": 594, "y": 1126, "width": 168, "height": 212}, {"x": 594, "y": 1128, "width": 168, "height": 212}, {"x": 596, "y": 1130, "width": 164, "height": 208}, {"x": 594, "y": 1128, "width": 164, "height": 208}, {"x": 596, "y": 1128, "width": 164, "height": 208}, {"x": 596, "y": 1128, "width": 164, "height": 208}, {"x": 596, "y": 1128, "width": 164, "height": 208}, {"x": 598, "y": 1128, "width": 164, "height": 208}, {"x": 596, "y": 1128, "width": 164, "height": 208}, {"x": 598, "y": 1128, "width": 164, "height": 208}, {"x": 596, "y": 1128, "width": 164, "height": 208}, {"x": 596, "y": 1128, "width": 164, "height": 208}, {"x": 596, "y": 1128, "width": 164, "height": 208}, {"x": 598, "y": 1128, "width": 164, "height": 208}, {"x": 598, "y": 1128, "width": 164, "height": 208}, {"x": 598, "y": 1128, "width": 164, "height": 208}, {"x": 598, "y": 1128, "width": 164, "height": 208}, {"x": 596, "y": 1128, "width": 164, "height": 208}, {"x": 598, "y": 1128, "width": 164, "height": 208}, {"x": 598, "y": 1128, "width": 164, "height": 208}, {"x": 596, "y": 1126, "width": 168, "height": 212}, {"x": 598, "y": 1128, "width": 168, "height": 212}, {"x": 596, "y": 1128, "width": 168, "height": 212}, {"x": 598, "y": 1130, "width": 164, "height": 208}, {"x": 598, "y": 1128, "width": 164, "height": 208}, {"x": 596, "y": 1128, "width": 164, "height": 208}, {"x": 598, "y": 1128, "width": 164, "height": 208}, {"x": 596, "y": 1128, "width": 164, "height": 208}, {"x": 598, "y": 1128, "width": 164, "height": 208}, {"x": 596, "y": 1128, "width": 164, "height": 208}, {"x": 596, "y": 1128, "width": 164, "height": 208}, {"x": 596, "y": 1126, "width": 164, "height": 208}, {"x": 598, "y": 1126, "width": 164, "height": 208}, {"x": 598, "y": 1128, "width": 164, "height": 208}, {"x": 596, "y": 1126, "width": 164, "height": 208}, {"x": 596, "y": 1126, "width": 164, "height": 208}, {"x": 596, "y": 1126, "width": 164, "height": 208}, {"x": 596, "y": 1124, "width": 164, "height": 208}, {"x": 596, "y": 1126, "width": 164, "height": 208}, {"x": 596, "y": 1124, "width": 164, "height": 208}, {"x": 596, "y": 1124, "width": 164, "height": 208}, {"x": 596, "y": 1124, "width": 164, "height": 208}, {"x": 596, "y": 1124, "width": 164, "height": 208}, {"x": 596, "y": 1124, "width": 164, "height": 208}, {"x": 596, "y": 1124, "width": 164, "height": 208}, {"x": 596, "y": 1124, "width": 164, "height": 208}, {"x": 596, "y": 1124, "width": 164, "height": 208}, {"x": 596, "y": 1124, "width": 164, "height": 208}, {"x": 596, "y": 1124, "width": 168, "height": 212}, {"x": 596, "y": 1124, "width": 168, "height": 212}, {"x": 596, "y": 1122, "width": 170, "height": 216}, {"x": 596, "y": 1122, "width": 170, "height": 216}, {"x": 596, "y": 1122, "width": 170, "height": 216}, {"x": 598, "y": 1122, "width": 170, "height": 216}, {"x": 598, "y": 1122, "width": 170, "height": 216}, {"x": 602, "y": 1126, "width": 168, "height": 212}, {"x": 602, "y": 1126, "width": 168, "height": 212}, {"x": 602, "y": 1126, "width": 168, "height": 212}, {"x": 602, "y": 1126, "width": 168, "height": 212}, {"x": 604, "y": 1128, "width": 164, "height": 208}, {"x": 602, "y": 1128, "width": 164, "height": 208}, {"x": 602, "y": 1126, "width": 164, "height": 208}, {"x": 602, "y": 1126, "width": 164, "height": 208}, {"x": 602, "y": 1126, "width": 164, "height": 208}, {"x": 602, "y": 1126, "width": 164, "height": 208}, {"x": 604, "y": 1128, "width": 160, "height": 204}, {"x": 604, "y": 1128, "width": 164, "height": 208}, {"x": 604, "y": 1126, "width": 164, "height": 208}, {"x": 602, "y": 1126, "width": 164, "height": 208}, {"x": 604, "y": 1126, "width": 164, "height": 208}, {"x": 604, "y": 1124, "width": 164, "height": 208}, {"x": 604, "y": 1126, "width": 164, "height": 208}, {"x": 604, "y": 1126, "width": 164, "height": 208}, {"x": 606, "y": 1126, "width": 164, "height": 208}, {"x": 606, "y": 1126, "width": 164, "height": 208}, {"x": 606, "y": 1126, "width": 164, "height": 208}, {"x": 606, "y": 1126, "width": 164, "height": 208}, {"x": 606, "y": 1126, "width": 164, "height": 208}, {"x": 608, "y": 1126, "width": 164, "height": 208}, {"x": 608, "y": 1126, "width": 164, "height": 208}, {"x": 608, "y": 1126, "width": 164, "height": 208}, {"x": 606, "y": 1126, "width": 164, "height": 208}, {"x": 606, "y": 1124, "width": 164, "height": 208}, {"x": 606, "y": 1124, "width": 164, "height": 208}, {"x": 606, "y": 1124, "width": 164, "height": 208}, {"x": 608, "y": 1124, "width": 164, "height": 208}, {"x": 608, "y": 1124, "width": 164, "height": 208}, {"x": 608, "y": 1124, "width": 164, "height": 208}, {"x": 608, "y": 1124, "width": 164, "height": 208}, {"x": 610, "y": 1126, "width": 160, "height": 204}, {"x": 610, "y": 1126, "width": 164, "height": 208}, {"x": 608, "y": 1124, "width": 164, "height": 208}, {"x": 610, "y": 1126, "width": 164, "height": 208}, {"x": 610, "y": 1126, "width": 164, "height": 208}, {"x": 610, "y": 1128, "width": 160, "height": 204}, {"x": 612, "y": 1130, "width": 160, "height": 204}, {"x": 610, "y": 1130, "width": 160, "height": 204}, {"x": 610, "y": 1128, "width": 164, "height": 208}, {"x": 608, "y": 1128, "width": 164, "height": 208}, {"x": 608, "y": 1128, "width": 164, "height": 208}, {"x": 610, "y": 1130, "width": 160, "height": 204}, {"x": 610, "y": 1130, "width": 164, "height": 208}, {"x": 608, "y": 1128, "width": 164, "height": 208}, {"x": 608, "y": 1128, "width": 164, "height": 208}, {"x": 608, "y": 1128, "width": 164, "height": 208}, {"x": 608, "y": 1128, "width": 164, "height": 208}, {"x": 610, "y": 1130, "width": 160, "height": 204}, {"x": 612, "y": 1132, "width": 160, "height": 204}, {"x": 610, "y": 1132, "width": 160, "height": 204}, {"x": 610, "y": 1130, "width": 164, "height": 208}, {"x": 608, "y": 1128, "width": 164, "height": 208}, {"x": 612, "y": 1132, "width": 158, "height": 200}, {"x": 612, "y": 1132, "width": 158, "height": 200}, {"x": 610, "y": 1130, "width": 160, "height": 204}, {"x": 610, "y": 1128, "width": 164, "height": 208}, {"x": 610, "y": 1128, "width": 164, "height": 208}, {"x": 610, "y": 1128, "width": 164, "height": 208}, {"x": 610, "y": 1128, "width": 164, "height": 208}, {"x": 610, "y": 1128, "width": 164, "height": 208}, {"x": 610, "y": 1128, "width": 164, "height": 208}, {"x": 610, "y": 1128, "width": 164, "height": 208}, {"x": 610, "y": 1130, "width": 160, "height": 204}, {"x": 612, "y": 1130, "width": 164, "height": 208}, {"x": 608, "y": 1128, "width": 164, "height": 208}, {"x": 608, "y": 1128, "width": 164, "height": 208}, {"x": 608, "y": 1128, "width": 164, "height": 208}, {"x": 608, "y": 1128, "width": 164, "height": 208}, {"x": 610, "y": 1130, "width": 160, "height": 204}, {"x": 610, "y": 1130, "width": 164, "height": 208}, {"x": 608, "y": 1128, "width": 164, "height": 208}, {"x": 608, "y": 1128, "width": 164, "height": 208}, {"x": 608, "y": 1130, "width": 164, "height": 208}, {"x": 608, "y": 1130, "width": 164, "height": 208}, {"x": 608, "y": 1130, "width": 164, "height": 208}, {"x": 608, "y": 1130, "width": 164, "height": 208}, {"x": 608, "y": 1130, "width": 164, "height": 208}, {"x": 608, "y": 1130, "width": 164, "height": 208}, {"x": 610, "y": 1130, "width": 160, "height": 204}, {"x": 610, "y": 1130, "width": 164, "height": 208}, {"x": 610, "y": 1128, "width": 164, "height": 208}, {"x": 608, "y": 1130, "width": 164, "height": 208}, {"x": 608, "y": 1130, "width": 164, "height": 208}, {"x": 610, "y": 1132, "width": 160, "height": 204}, {"x": 610, "y": 1132, "width": 164, "height": 208}, {"x": 608, "y": 1130, "width": 164, "height": 208}, {"x": 608, "y": 1130, "width": 164, "height": 208}, {"x": 608, "y": 1132, "width": 160, "height": 204}, {"x": 610, "y": 1130, "width": 164, "height": 208}, {"x": 608, "y": 1130, "width": 164, "height": 208}, {"x": 608, "y": 1130, "width": 164, "height": 208}, {"x": 608, "y": 1128, "width": 164, "height": 208}, {"x": 610, "y": 1130, "width": 160, "height": 204}, {"x": 610, "y": 1130, "width": 164, "height": 208}, {"x": 610, "y": 1130, "width": 160, "height": 204}, {"x": 612, "y": 1132, "width": 160, "height": 204}, {"x": 608, "y": 1130, "width": 164, "height": 208}, {"x": 606, "y": 1128, "width": 164, "height": 208}, {"x": 608, "y": 1130, "width": 160, "height": 204}, {"x": 608, "y": 1128, "width": 164, "height": 208}, {"x": 608, "y": 1130, "width": 160, "height": 204}, {"x": 610, "y": 1130, "width": 160, "height": 204}, {"x": 610, "y": 1130, "width": 160, "height": 204}, {"x": 610, "y": 1130, "width": 160, "height": 204}, {"x": 608, "y": 1126, "width": 164, "height": 208}, {"x": 606, "y": 1126, "width": 164, "height": 208}, {"x": 608, "y": 1128, "width": 160, "height": 204}, {"x": 610, "y": 1130, "width": 160, "height": 204}, {"x": 610, "y": 1130, "width": 160, "height": 204}, {"x": 610, "y": 1128, "width": 160, "height": 204}, {"x": 610, "y": 1128, "width": 164, "height": 208}, {"x": 608, "y": 1126, "width": 164, "height": 208}, {"x": 608, "y": 1128, "width": 160, "height": 204}, {"x": 608, "y": 1128, "width": 164, "height": 208}, {"x": 606, "y": 1126, "width": 164, "height": 208}, {"x": 608, "y": 1130, "width": 160, "height": 204}, {"x": 610, "y": 1130, "width": 160, "height": 204}, {"x": 608, "y": 1128, "width": 164, "height": 208}, {"x": 608, "y": 1128, "width": 160, "height": 204}, {"x": 608, "y": 1128, "width": 164, "height": 208}, {"x": 608, "y": 1128, "width": 164, "height": 208}, {"x": 610, "y": 1130, "width": 160, "height": 204}, {"x": 610, "y": 1132, "width": 160, "height": 204}, {"x": 610, "y": 1132, "width": 160, "height": 204}, {"x": 612, "y": 1132, "width": 160, "height": 204}, {"x": 610, "y": 1130, "width": 164, "height": 208}, {"x": 610, "y": 1130, "width": 160, "height": 204}, {"x": 610, "y": 1130, "width": 160, "height": 204}, {"x": 612, "y": 1132, "width": 160, "height": 204}, {"x": 610, "y": 1130, "width": 164, "height": 208}, {"x": 608, "y": 1130, "width": 164, "height": 208}, {"x": 610, "y": 1132, "width": 160, "height": 204}, {"x": 612, "y": 1134, "width": 160, "height": 204}, {"x": 608, "y": 1130, "width": 164, "height": 208}, {"x": 610, "y": 1132, "width": 160, "height": 204}, {"x": 610, "y": 1132, "width": 164, "height": 208}, {"x": 610, "y": 1130, "width": 164, "height": 208}, {"x": 610, "y": 1132, "width": 160, "height": 204}, {"x": 610, "y": 1130, "width": 164, "height": 208}, {"x": 610, "y": 1130, "width": 160, "height": 204}, {"x": 610, "y": 1130, "width": 164, "height": 208}, {"x": 612, "y": 1132, "width": 160, "height": 204}, {"x": 610, "y": 1132, "width": 164, "height": 208}, {"x": 608, "y": 1130, "width": 164, "height": 208}, {"x": 608, "y": 1132, "width": 160, "height": 204}, {"x": 610, "y": 1132, "width": 164, "height": 208}, {"x": 608, "y": 1130, "width": 164, "height": 208}, {"x": 608, "y": 1130, "width": 164, "height": 208}, {"x": 608, "y": 1130, "width": 164, "height": 208}, {"x": 608, "y": 1130, "width": 164, "height": 208}, {"x": 608, "y": 1130, "width": 164, "height": 208}, {"x": 608, "y": 1132, "width": 160, "height": 204}, {"x": 610, "y": 1132, "width": 164, "height": 208}, {"x": 608, "y": 1130, "width": 164, "height": 208}, {"x": 608, "y": 1130, "width": 164, "height": 208}, {"x": 608, "y": 1130, "width": 164, "height": 208}, {"x": 608, "y": 1130, "width": 164, "height": 208}, {"x": 610, "y": 1132, "width": 164, "height": 208}, {"x": 608, "y": 1130, "width": 164, "height": 208}, {"x": 608, "y": 1130, "width": 164, "height": 208}, {"x": 608, "y": 1130, "width": 164, "height": 208}, {"x": 608, "y": 1130, "width": 164, "height": 208}, {"x": 608, "y": 1130, "width": 164, "height": 208}, {"x": 610, "y": 1130, "width": 160, "height": 204}, {"x": 610, "y": 1130, "width": 164, "height": 208}, {"x": 608, "y": 1130, "width": 164, "height": 208}, {"x": 608, "y": 1132, "width": 160, "height": 204}, {"x": 608, "y": 1134, "width": 160, "height": 204}, {"x": 608, "y": 1134, "width": 160, "height": 204}, {"x": 602, "y": 1130, "width": 164, "height": 208}, {"x": 596, "y": 1126, "width": 168, "height": 212}, {"x": 594, "y": 1126, "width": 168, "height": 212}, {"x": 588, "y": 1126, "width": 164, "height": 208}, {"x": 586, "y": 1118, "width": 164, "height": 208}, {"x": 580, "y": 1124, "width": 160, "height": 204}, {"x": 580, "y": 1126, "width": 160, "height": 204}, {"x": 580, "y": 1128, "width": 160, "height": 204}, {"x": 580, "y": 1128, "width": 160, "height": 204}, {"x": 578, "y": 1126, "width": 164, "height": 208}, {"x": 576, "y": 1120, "width": 164, "height": 208}, {"x": 572, "y": 1116, "width": 168, "height": 212}, {"x": 576, "y": 1116, "width": 168, "height": 212}, {"x": 576, "y": 1112, "width": 168, "height": 212}, {"x": 580, "y": 1112, "width": 168, "height": 212}, {"x": 580, "y": 1106, "width": 168, "height": 212}, {"x": 576, "y": 1102, "width": 170, "height": 216}, {"x": 578, "y": 1100, "width": 170, "height": 216}, {"x": 578, "y": 1098, "width": 170, "height": 216}, {"x": 580, "y": 1100, "width": 170, "height": 216}, {"x": 582, "y": 1100, "width": 170, "height": 216}, {"x": 584, "y": 1098, "width": 174, "height": 220}, {"x": 588, "y": 1100, "width": 174, "height": 220}, {"x": 588, "y": 1100, "width": 174, "height": 220}, {"x": 590, "y": 1100, "width": 178, "height": 226}, {"x": 590, "y": 1100, "width": 178, "height": 226}, {"x": 592, "y": 1100, "width": 178, "height": 226}, {"x": 592, "y": 1102, "width": 178, "height": 226}, {"x": 588, "y": 1100, "width": 180, "height": 230}, {"x": 588, "y": 1102, "width": 180, "height": 230}, {"x": 588, "y": 1104, "width": 178, "height": 226}, {"x": 588, "y": 1106, "width": 178, "height": 226}, {"x": 586, "y": 1106, "width": 178, "height": 226}, {"x": 586, "y": 1108, "width": 178, "height": 226}, {"x": 584, "y": 1110, "width": 178, "height": 226}, {"x": 586, "y": 1110, "width": 178, "height": 226}, {"x": 586, "y": 1112, "width": 178, "height": 226}, {"x": 588, "y": 1114, "width": 178, "height": 226}, {"x": 590, "y": 1114, "width": 178, "height": 226}, {"x": 588, "y": 1110, "width": 180, "height": 230}, {"x": 588, "y": 1112, "width": 180, "height": 230}, {"x": 588, "y": 1112, "width": 180, "height": 230}, {"x": 588, "y": 1112, "width": 180, "height": 230}, {"x": 590, "y": 1112, "width": 180, "height": 230}, {"x": 592, "y": 1114, "width": 180, "height": 230}, {"x": 592, "y": 1112, "width": 180, "height": 230}, {"x": 594, "y": 1116, "width": 178, "height": 226}, {"x": 592, "y": 1114, "width": 178, "height": 226}, {"x": 590, "y": 1116, "width": 178, "height": 226}, {"x": 590, "y": 1116, "width": 178, "height": 226}, {"x": 588, "y": 1116, "width": 178, "height": 226}, {"x": 586, "y": 1116, "width": 178, "height": 226}, {"x": 586, "y": 1116, "width": 178, "height": 226}, {"x": 586, "y": 1116, "width": 178, "height": 226}, {"x": 586, "y": 1118, "width": 178, "height": 226}, {"x": 586, "y": 1118, "width": 178, "height": 226}, {"x": 586, "y": 1118, "width": 178, "height": 226}, {"x": 584, "y": 1118, "width": 178, "height": 226}, {"x": 586, "y": 1118, "width": 178, "height": 226}, {"x": 584, "y": 1118, "width": 178, "height": 226}, {"x": 586, "y": 1118, "width": 178, "height": 226}, {"x": 586, "y": 1118, "width": 174, "height": 220}, {"x": 588, "y": 1120, "width": 174, "height": 220}, {"x": 588, "y": 1120, "width": 174, "height": 220}, {"x": 588, "y": 1118, "width": 178, "height": 226}, {"x": 588, "y": 1118, "width": 174, "height": 220}, {"x": 590, "y": 1118, "width": 174, "height": 220}, {"x": 588, "y": 1116, "width": 178, "height": 226}, {"x": 588, "y": 1116, "width": 178, "height": 226}, {"x": 588, "y": 1118, "width": 178, "height": 226}, {"x": 588, "y": 1116, "width": 178, "height": 226}, {"x": 590, "y": 1118, "width": 174, "height": 220}, {"x": 590, "y": 1120, "width": 174, "height": 220}, {"x": 590, "y": 1120, "width": 174, "height": 220}, {"x": 590, "y": 1122, "width": 174, "height": 220}, {"x": 590, "y": 1122, "width": 174, "height": 220}, {"x": 590, "y": 1124, "width": 174, "height": 220}, {"x": 588, "y": 1126, "width": 174, "height": 220}, {"x": 590, "y": 1132, "width": 174, "height": 220}, {"x": 590, "y": 1134, "width": 174, "height": 220}, {"x": 588, "y": 1136, "width": 174, "height": 220}, {"x": 588, "y": 1138, "width": 174, "height": 220}, {"x": 590, "y": 1142, "width": 170, "height": 216}, {"x": 588, "y": 1144, "width": 170, "height": 216}, {"x": 588, "y": 1144, "width": 170, "height": 216}, {"x": 590, "y": 1140, "width": 168, "height": 212}, {"x": 590, "y": 1136, "width": 168, "height": 212}, {"x": 594, "y": 1136, "width": 164, "height": 208}, {"x": 594, "y": 1132, "width": 164, "height": 208}, {"x": 596, "y": 1130, "width": 164, "height": 208}, {"x": 598, "y": 1126, "width": 164, "height": 208}, {"x": 602, "y": 1126, "width": 164, "height": 208}, {"x": 604, "y": 1126, "width": 164, "height": 208}, {"x": 604, "y": 1126, "width": 164, "height": 208}, {"x": 606, "y": 1126, "width": 160, "height": 204}, {"x": 610, "y": 1126, "width": 160, "height": 204}, {"x": 608, "y": 1126, "width": 164, "height": 208}, {"x": 606, "y": 1126, "width": 164, "height": 208}, {"x": 606, "y": 1126, "width": 164, "height": 208}, {"x": 606, "y": 1126, "width": 164, "height": 208}, {"x": 604, "y": 1126, "width": 164, "height": 208}, {"x": 604, "y": 1128, "width": 160, "height": 204}, {"x": 606, "y": 1132, "width": 160, "height": 204}, {"x": 604, "y": 1132, "width": 160, "height": 204}, {"x": 602, "y": 1132, "width": 160, "height": 204}, {"x": 604, "y": 1134, "width": 160, "height": 204}, {"x": 602, "y": 1134, "width": 160, "height": 204}, {"x": 602, "y": 1134, "width": 160, "height": 204}, {"x": 602, "y": 1134, "width": 160, "height": 204}, {"x": 602, "y": 1134, "width": 160, "height": 204}, {"x": 602, "y": 1134, "width": 160, "height": 204}, {"x": 602, "y": 1132, "width": 164, "height": 208}, {"x": 602, "y": 1134, "width": 160, "height": 204}, {"x": 602, "y": 1134, "width": 160, "height": 204}, {"x": 604, "y": 1134, "width": 160, "height": 204}, {"x": 602, "y": 1132, "width": 160, "height": 204}, {"x": 604, "y": 1134, "width": 160, "height": 204}, {"x": 602, "y": 1132, "width": 164, "height": 208}, {"x": 598, "y": 1130, "width": 164, "height": 208}, {"x": 602, "y": 1134, "width": 160, "height": 204}, {"x": 604, "y": 1136, "width": 160, "height": 204}, {"x": 602, "y": 1136, "width": 160, "height": 204}, {"x": 602, "y": 1134, "width": 160, "height": 204}, {"x": 602, "y": 1134, "width": 160, "height": 204}, {"x": 602, "y": 1134, "width": 160, "height": 204}, {"x": 602, "y": 1134, "width": 160, "height": 204}, {"x": 600, "y": 1132, "width": 164, "height": 208}, {"x": 598, "y": 1130, "width": 164, "height": 208}, {"x": 598, "y": 1130, "width": 164, "height": 208}, {"x": 600, "y": 1132, "width": 160, "height": 204}, {"x": 602, "y": 1136, "width": 158, "height": 200}, {"x": 598, "y": 1134, "width": 160, "height": 204}, {"x": 598, "y": 1136, "width": 158, "height": 200}, {"x": 596, "y": 1136, "width": 158, "height": 200}, {"x": 598, "y": 1138, "width": 158, "height": 200}, {"x": 598, "y": 1140, "width": 158, "height": 200}, {"x": 598, "y": 1144, "width": 154, "height": 196}, {"x": 600, "y": 1146, "width": 154, "height": 196}, {"x": 598, "y": 1148, "width": 154, "height": 196}, {"x": 600, "y": 1150, "width": 154, "height": 196}, {"x": 602, "y": 1152, "width": 154, "height": 196}, {"x": 600, "y": 1156, "width": 154, "height": 196}, {"x": 600, "y": 1158, "width": 154, "height": 196}, {"x": 598, "y": 1150, "width": 154, "height": 196}, {"x": 608, "y": 1138, "width": 154, "height": 196}, {"x": 608, "y": 1136, "width": 154, "height": 196}, {"x": 610, "y": 1136, "width": 154, "height": 196}, {"x": 610, "y": 1134, "width": 154, "height": 196}, {"x": 610, "y": 1132, "width": 154, "height": 196}, {"x": 610, "y": 1130, "width": 154, "height": 196}, {"x": 610, "y": 1128, "width": 158, "height": 200}, {"x": 610, "y": 1128, "width": 158, "height": 200}, {"x": 614, "y": 1128, "width": 158, "height": 200}, {"x": 614, "y": 1126, "width": 158, "height": 200}, {"x": 612, "y": 1124, "width": 158, "height": 200}, {"x": 612, "y": 1124, "width": 158, "height": 200}, {"x": 612, "y": 1124, "width": 158, "height": 200}, {"x": 612, "y": 1124, "width": 158, "height": 200}, {"x": 612, "y": 1124, "width": 158, "height": 200}, {"x": 612, "y": 1122, "width": 158, "height": 200}, {"x": 610, "y": 1122, "width": 160, "height": 204}, {"x": 612, "y": 1124, "width": 160, "height": 204}, {"x": 612, "y": 1124, "width": 160, "height": 204}, {"x": 610, "y": 1122, "width": 164, "height": 208}, {"x": 608, "y": 1122, "width": 164, "height": 208}, {"x": 610, "y": 1126, "width": 160, "height": 204}, {"x": 612, "y": 1128, "width": 160, "height": 204}, {"x": 612, "y": 1128, "width": 160, "height": 204}, {"x": 614, "y": 1132, "width": 158, "height": 200}, {"x": 612, "y": 1132, "width": 158, "height": 200}, {"x": 612, "y": 1132, "width": 158, "height": 200}, {"x": 612, "y": 1132, "width": 158, "height": 200}, {"x": 612, "y": 1132, "width": 158, "height": 200}, {"x": 610, "y": 1132, "width": 158, "height": 200}, {"x": 612, "y": 1132, "width": 158, "height": 200}, {"x": 612, "y": 1132, "width": 158, "height": 200}, {"x": 612, "y": 1132, "width": 158, "height": 200}, {"x": 614, "y": 1134, "width": 154, "height": 196}, {"x": 614, "y": 1132, "width": 158, "height": 200}, {"x": 610, "y": 1130, "width": 158, "height": 200}, {"x": 614, "y": 1132, "width": 158, "height": 200}, {"x": 612, "y": 1132, "width": 158, "height": 200}, {"x": 612, "y": 1134, "width": 158, "height": 200}, {"x": 612, "y": 1134, "width": 158, "height": 200}, {"x": 610, "y": 1134, "width": 158, "height": 200}, {"x": 612, "y": 1134, "width": 158, "height": 200}, {"x": 610, "y": 1134, "width": 158, "height": 200}, {"x": 612, "y": 1134, "width": 158, "height": 200}, {"x": 610, "y": 1132, "width": 158, "height": 200}, {"x": 612, "y": 1134, "width": 158, "height": 200}, {"x": 612, "y": 1132, "width": 158, "height": 200}, {"x": 612, "y": 1134, "width": 158, "height": 200}, {"x": 612, "y": 1134, "width": 158, "height": 200}, {"x": 610, "y": 1132, "width": 158, "height": 200}, {"x": 612, "y": 1134, "width": 158, "height": 200}, {"x": 610, "y": 1132, "width": 158, "height": 200}, {"x": 612, "y": 1134, "width": 158, "height": 200}, {"x": 610, "y": 1134, "width": 158, "height": 200}, {"x": 610, "y": 1134, "width": 158, "height": 200}, {"x": 610, "y": 1134, "width": 158, "height": 200}, {"x": 610, "y": 1134, "width": 158, "height": 200}, {"x": 610, "y": 1132, "width": 158, "height": 200}, {"x": 610, "y": 1134, "width": 158, "height": 200}, {"x": 608, "y": 1134, "width": 158, "height": 200}, {"x": 610, "y": 1134, "width": 158, "height": 200}, {"x": 608, "y": 1134, "width": 158, "height": 200}, {"x": 610, "y": 1136, "width": 154, "height": 196}, {"x": 610, "y": 1134, "width": 158, "height": 200}, {"x": 610, "y": 1136, "width": 154, "height": 196}, {"x": 612, "y": 1138, "width": 154, "height": 196}, {"x": 610, "y": 1138, "width": 154, "height": 196}, {"x": 612, "y": 1140, "width": 154, "height": 196}, {"x": 612, "y": 1138, "width": 154, "height": 196}, {"x": 610, "y": 1138, "width": 154, "height": 196}, {"x": 610, "y": 1136, "width": 158, "height": 200}, {"x": 608, "y": 1136, "width": 158, "height": 200}, {"x": 610, "y": 1138, "width": 158, "height": 200}, {"x": 608, "y": 1136, "width": 158, "height": 200}, {"x": 608, "y": 1136, "width": 158, "height": 200}, {"x": 608, "y": 1136, "width": 158, "height": 200}, {"x": 610, "y": 1138, "width": 154, "height": 196}, {"x": 610, "y": 1138, "width": 154, "height": 196}, {"x": 610, "y": 1136, "width": 158, "height": 200}, {"x": 608, "y": 1134, "width": 158, "height": 200}, {"x": 608, "y": 1136, "width": 158, "height": 200}, {"x": 608, "y": 1136, "width": 158, "height": 200}, {"x": 608, "y": 1134, "width": 158, "height": 200}, {"x": 608, "y": 1134, "width": 158, "height": 200}, {"x": 610, "y": 1134, "width": 158, "height": 200}, {"x": 606, "y": 1132, "width": 160, "height": 204}, {"x": 608, "y": 1134, "width": 160, "height": 204}]